.travis.yml
AUTHORS
ChangeLog
LICENSE
README.rst
VERSION
requirements.txt
setup.cfg
setup.py
helcli/__init__.py
helcli/config.py
helcli/parser.py
helcli.egg-info/PKG-INFO
helcli.egg-info/SOURCES.txt
helcli.egg-info/dependency_links.txt
helcli.egg-info/not-zip-safe
helcli.egg-info/pbr.json
helcli.egg-info/requires.txt
helcli.egg-info/top_level.txt